game/__init__.py
game/__main__.py
game/assets.py
game/config.json
game/config.py
game/debug_overlay.py
game/main.py
game/sound_manager.py
game/games/__init__.py
game/games/arkanoid.py
game/games/base.py
game/games/logic.py
game/games/pacman.py
game/games/snake.py
game/games/tetris.py
game/ui/__init__.py
game/ui/menu.py
game/ui/scores.py
game_collection-1.2.0.dist-info/licenses/LICENSE
game_collection-1.2.0.dist-info/METADATA
game_collection-1.2.0.dist-info/WHEEL
game_collection-1.2.0.dist-info/entry_points.txt
game_collection-1.2.0.dist-info/top_level.txt
game_collection-1.2.0.dist-info/RECORD
