Metadata-Version: 2.4
Name: game-collection
Version: 1.2.0
Summary: 🎮 Коллекция классических аркадных игр: Snake, Tetris, Arkanoid и Pac-Man на Python с Pygame
Author-email: Sergey <hleserg@example.com>
License-Expression: MIT
Project-URL: Homepage, https://github.com/hleserg/game
Project-URL: Repository, https://github.com/hleserg/game
Project-URL: Issues, https://github.com/hleserg/game/issues
Project-URL: Changelog, https://github.com/hleserg/game/blob/main/CHANGELOG.md
Keywords: games,arcade,pygame,snake,tetris,arkanoid,pacman,python,игры,аркада,змейка,тетрис,арканоид,пакман
Classifier: Development Status :: 5 - Production/Stable
Classifier: Intended Audience :: End Users/Desktop
Classifier: Operating System :: OS Independent
Classifier: Programming Language :: Python :: 3
Classifier: Programming Language :: Python :: 3.10
Classifier: Programming Language :: Python :: 3.11
Classifier: Programming Language :: Python :: 3.12
Classifier: Topic :: Games/Entertainment
Requires-Python: >=3.10
License-File: LICENSE
Requires-Dist: pygame>=2.5.0
Requires-Dist: appdirs>=1.4.4
Provides-Extra: dev
Requires-Dist: ruff>=0.1.0; extra == "dev"
Requires-Dist: mypy>=1.8.0; extra == "dev"
Requires-Dist: pytest>=7.4.0; extra == "dev"
Requires-Dist: pytest-cov>=4.1.0; extra == "dev"
Requires-Dist: pyinstaller>=5.13.0; extra == "dev"
Requires-Dist: appdirs>=1.4.4; extra == "dev"
Requires-Dist: pre-commit>=3.6.0; extra == "dev"
Requires-Dist: bandit>=1.7.5; extra == "dev"
Requires-Dist: pydocstyle>=6.3.0; extra == "dev"
Dynamic: license-file
